{
    "id": 109864707,
    "name": "Dash Challenge",
    "author": "Tooperwooper",
    "creators": [],
    "verifier": "SchwertBootGD",
    "verification": "https://youtu.be/WBnXs4Lblr0",
    "percentToQualify": "50",
    "password": "Free To Copy",
    "records": [
        {
            "user": "Firewyrm",
            "link": "https://youtu.be/rBOi6apHYf8",
            "percent": 100,
            "hz": 60
        },
        {
            "user": "CatsAtGD54",
            "link": "https://www.youtube.com/watch?v=rbAjnzV7W7g",
            "percent": 100,
            "hz": 480
        },
        {
            "user": "Nemo",
            "link": "https://youtu.be/gnlMoPE8VD4",
            "percent": 100,
            "hz": 240
        },
        {
            "user": "TheChampion210",
            "link": "https://www.youtube.com/watch?v=D6rAlYOvlIo",
            "percent": 100,
            "hz": 150
        },
        {
            "user": "cheesearmy1",
            "link": "https://www.youtube.com/watch?v=iY6ujm3SD7A",
            "percent": 100,
            "mobile": true,
            "hz": 120
        },
        {
            "user": "MineproGD",
            "link": "https://www.youtube.com/watch?v=TQt5zV-EcdU",
            "percent": 100,
            "hz": 60
        },
        {
            "user": "IkukGD",
            "link": "https://youtu.be/xQtXyGSsqh0?si=uh3UHrMnEVV5wrHB",
            "percent": 100,
            "mobile": true,
            "hz": 90
        },
        {
            "user": "Chloe",
            "link": "https://www.youtube.com/watch?v=MmW1j5AGGd0",
            "percent": 100,
            "mobile": false,
            "hz": 240
        },
        {
            "user": "astral",
            "link": "https://youtube.com/shorts/2-DCINLlKio?si=-xQm5BzPHIYB931k",
            "percent": 100,
            "mobile": true,
            "hz": 90
        },
        {
            "user": "adrjbv",
            "link": "https://youtu.be/xXERk_QS7nk",
            "percent": 100,
            "mobile": false,
            "hz": 60
        },
        {
            "user": "Tariok",
            "link": "https://youtu.be/dUC6s_FmJlE?si=5XBBOcradZdU-I6t",
            "percent": 100,
            "mobile": true,
            "hz": 60
        },
        {
            "user": "LetzTiz",
            "link": "https://youtu.be/_ER_GgHnFfM?si=ACZlzUBWqYfm7W4d",
            "percent": 100,
            "mobile": false,
            "hz": 800
        },
        {
            "user": "Ali",
            "link": "https://youtu.be/c7TT3RSxsL0",
            "percent": 100,
            "mobile": false,
            "hz": 60
        }
    ]
}
